ng_ai/__init__.py
ng_ai/config.py
ng_ai/engines.py
ng_ai/nebula_algo.py
ng_ai/nebula_data.py
ng_ai/nebula_gnn.py
ng_ai/nebula_reader.py
ng_ai/nebula_writer.py
ng_ai/ng_ai_api/__init__.py
ng_ai/ng_ai_api/__main__.py
ng_ai/ng_ai_api/app.py
ng_ai-0.2.10.3.dist-info/WHEEL
ng_ai-0.2.10.3.dist-info/METADATA
ng_ai-0.2.10.3.dist-info/licenses/LICENSE
ng_ai-0.2.10.3.dist-info/RECORD
