Metadata-Version: 2.1
Name: ng_ai
Version: 0.2.10.3
Summary: NebulaGraph AI Suite
License: Apache-2.0
Author-email: Wey Gu <weyl.gu@gmail.com>
Requires-Python: >=3.7.1,<3.10
Classifier: Programming Language :: Python :: 3
Classifier: Programming Language :: Python :: 3.10
Classifier: Programming Language :: Python :: 3.7
Classifier: Programming Language :: Python :: 3.8
Classifier: Programming Language :: Python :: 3.9
Classifier: Topic :: Software Development :: Build Tools
Requires-Dist: flask>=2.0.3
Provides-Extra: all
Requires-Dist: ng_ai[networkx,spark]; extra == "all"
Provides-Extra: dev
Requires-Dist: ng_ai[all,lint,test]; extra == "dev"
Provides-Extra: jupyter
Requires-Dist: jupyter_nebulagraph>=0.14.3; extra == "jupyter"
Provides-Extra: lint
Requires-Dist: flake8>=4.0.1; extra == "lint"
Requires-Dist: black[jupyter]>=23.1.0; extra == "lint"
Requires-Dist: isort>=5.11.5; extra == "lint"
Provides-Extra: networkx
Requires-Dist: ng_nx>=0.2.3; extra == "networkx"
Requires-Dist: gensim==4.1.0; extra == "networkx"
Requires-Dist: node2vec>=0.4.3; extra == "networkx"
Requires-Dist: python-louvain>=0.16; extra == "networkx"
Provides-Extra: spark
Requires-Dist: pyspark>=3.2.3; extra == "spark"
Provides-Extra: test
Requires-Dist: pytest>=7.2.2; extra == "test"
Requires-Dist: chispa>=0.9.2; extra == "test"
Requires-Dist: nebula3-python; extra == "test"
Project-URL: Changelog, https://github.com/wey-gu/nebulagraph-ai/releases
Project-URL: Documentation, https://github.com/wey-gu/nebulagraph-ai#documentation
Project-URL: Homepage, https://github.com/wey-gu/nebulagraph-ai
Project-URL: Repository, https://github.com/wey-gu/nebulagraph-ai
